main.py
pauron-0.1.2.dist-info/licenses/LICENSE
pauron-0.1.2.dist-info/METADATA
pauron-0.1.2.dist-info/WHEEL
pauron-0.1.2.dist-info/entry_points.txt
pauron-0.1.2.dist-info/top_level.txt
pauron-0.1.2.dist-info/RECORD
