Metadata-Version: 2.4
Name: pauron
Version: 0.1.2
Summary: AUR Automation Bot
Requires-Python: >=3.13
License-File: LICENSE
Requires-Dist: requests>=2.32.4
Dynamic: license-file
